LICENSE
README.md
setup.cfg
setup.py
px_django_lingua.egg-info/PKG-INFO
px_django_lingua.egg-info/SOURCES.txt
px_django_lingua.egg-info/dependency_links.txt
px_django_lingua.egg-info/requires.txt
px_django_lingua.egg-info/top_level.txt
pxd_lingua/__init__.py
pxd_lingua/admin.py
pxd_lingua/apps.py
pxd_lingua/conf.py
pxd_lingua/db.py
pxd_lingua/exceptions.py
pxd_lingua/loader.py
pxd_lingua/magic.py
pxd_lingua/models.py
pxd_lingua/query.py
pxd_lingua/types.py
pxd_lingua/utils.py
tests/test_creation.py
tests/test_language_querying.py